mhsize/__init__.py
mhsize/mhsize.py
mhsize/tests.py
mhsize-0.0.3.dist-info/METADATA
mhsize-0.0.3.dist-info/RECORD
mhsize-0.0.3.dist-info/WHEEL
mhsize-0.0.3.dist-info/top_level.txt
