Metadata-Version: 2.1
Name: mhsize
Version: 0.0.3
Summary: Convert the size between human(more) size and bytes on python3
Home-page: UNKNOWN
Author: shingo818
Author-email: gmboomker@gmail.com
License: MIT License
Keywords: human,size,Convert
Platform: any
